photocopy/__init__.py
photocopy/photocopy.py
photocopy/version.py
photocopy-0.2.0.dist-info/entry_points.txt
photocopy-0.2.0.dist-info/LICENSE
photocopy-0.2.0.dist-info/WHEEL
photocopy-0.2.0.dist-info/METADATA
photocopy-0.2.0.dist-info/RECORD
