Metadata-Version: 2.1
Name: photocopy
Version: 0.2.0
Summary: Copy your photos from an SD card or camera to a specific directory.
Home-page: https://github.com/skorokithakis/photocopy/
License: UNKNOWN
Author: Stavros Korokithakis
Author-email: hi@stavros.io
Classifier: License :: OSI Approved :: MIT License
Requires-Dist: docopt >=0.6.2
Requires-Dist: exifread >=2.1.2
